timexseries/__init__.py
timexseries/data_ingestion.py
timexseries/data_prediction/__init__.py
timexseries/data_prediction/models/__init__.py
timexseries/data_prediction/models/arima_predictor.py
timexseries/data_prediction/models/exponentialsmoothing_predictor.py
timexseries/data_prediction/models/lstm_predictor.py
timexseries/data_prediction/models/mockup_predictor.py
timexseries/data_prediction/models/neuralprophet_predictor.py
timexseries/data_prediction/models/persistence_predictor.py
timexseries/data_prediction/models/predictor.py
timexseries/data_prediction/models/prophet_predictor.py
timexseries/data_prediction/pipeline.py
timexseries/data_prediction/transformation.py
timexseries/data_prediction/validation_performances.py
timexseries/data_prediction/xcorr.py
timexseries/data_visualization/__init__.py
timexseries/data_visualization/functions.py
timexseries/data_visualization/locales/base.pot
timexseries/data_visualization/locales/en/LC_MESSAGES/messages.mo
timexseries/data_visualization/locales/en/LC_MESSAGES/messages.po
timexseries/data_visualization/locales/it/LC_MESSAGES/messages.mo
timexseries/data_visualization/locales/it/LC_MESSAGES/messages.po
timexseries/documentation.md
timexseries/timeseries_container.py
timexseries-1.2.3.dist-info/LICENSE
timexseries-1.2.3.dist-info/WHEEL
timexseries-1.2.3.dist-info/METADATA
timexseries-1.2.3.dist-info/RECORD
