Metadata-Version: 2.1
Name: timexseries
Version: 1.2.3
Summary: TIMEX is a framework for time-series-forecasting-as-a-service.
Home-page: https://alexmv12.github.io/TIMEX/
License: Apache-2.0
Keywords: time-series,time,forecasting,as-a-service
Author: Alessandro Falcetta
Author-email: alessandro.falcetta@polimi.it
Requires-Python: >=3.7,<3.11
Classifier: License :: OSI Approved :: Apache Software License
Classifier: Programming Language :: Python :: 3
Classifier: Programming Language :: Python :: 3.10
Classifier: Programming Language :: Python :: 3.7
Classifier: Programming Language :: Python :: 3.8
Classifier: Programming Language :: Python :: 3.9
Classifier: Topic :: Scientific/Engineering :: Information Analysis
Classifier: Topic :: Scientific/Engineering :: Mathematics
Requires-Dist: colorhash (>=1.0.4,<2.0.0)
Requires-Dist: dash (>=2.0.0,<3.0.0)
Requires-Dist: dash-bootstrap-components (>=1.0.3,<2.0.0)
Requires-Dist: dateparser (>=1.1.0,<2.0.0)
Requires-Dist: gunicorn (>=20.1.0,<21.0.0)
Requires-Dist: networkx (>=2.6.3,<3.0.0)
Requires-Dist: pmdarima (>=1.8.4,<2.0.0)
Requires-Dist: prophet (>=1.0.1,<2.0.0)
Requires-Dist: scipy (>=1.7.3,<2.0.0)
Requires-Dist: sklearn (>=0.0,<0.1)
Requires-Dist: statsmodels (>=0.13.1,<0.14.0)
Requires-Dist: torch (>=1.10.1,<2.0.0)
Project-URL: Repository, https://github.com/AlexMV12/TIMEX
